sandboxes/__init__.py
sandboxes/base.py
sandboxes/cli.py
sandboxes/exceptions.py
sandboxes/manager.py
sandboxes/pool.py
sandboxes/retry.py
sandboxes/sandbox.py
sandboxes/security.py
sandboxes/providers/__init__.py
sandboxes/providers/cloudflare.py
sandboxes/providers/daytona.py
sandboxes/providers/e2b.py
sandboxes/providers/hopx.py
sandboxes/providers/modal.py
sandboxes/providers/sprites.py
cased_sandboxes-0.5.0.dist-info/METADATA
cased_sandboxes-0.5.0.dist-info/WHEEL
cased_sandboxes-0.5.0.dist-info/entry_points.txt
cased_sandboxes-0.5.0.dist-info/licenses/LICENSE
cased_sandboxes-0.5.0.dist-info/RECORD
