Metadata-Version: 2.4
Name: cased-sandboxes
Version: 0.5.0
Summary: Universal library for AI code execution sandboxes
Author-email: Sandboxes Contributors <ted@cased.com>
License-Expression: MIT
License-File: LICENSE
Keywords: ai,cloudflare,code-execution,daytona,e2b,hopx,modal,sandbox,vercel
Classifier: Development Status :: 3 - Alpha
Classifier: Intended Audience :: Developers
Classifier: License :: OSI Approved :: MIT License
Classifier: Programming Language :: Python :: 3
Classifier: Programming Language :: Python :: 3.11
Classifier: Programming Language :: Python :: 3.12
Classifier: Topic :: Software Development :: Libraries
Requires-Python: >=3.11
Requires-Dist: click>=8.0.0
Requires-Dist: daytona>=0.103.0
Requires-Dist: e2b>=2.0.0
Requires-Dist: hopx-ai>=0.3.0
Requires-Dist: httpx>=0.27.0
Requires-Dist: modal>=1.1.4
Requires-Dist: tabulate>=0.9.0
Requires-Dist: typing-extensions>=4.0.0
Provides-Extra: all
Requires-Dist: daytona==0.103.0; extra == 'all'
Requires-Dist: e2b>=2.0.0; extra == 'all'
Requires-Dist: hopx-ai>=0.3.0; extra == 'all'
Requires-Dist: modal==1.1.4; extra == 'all'
Provides-Extra: daytona
Requires-Dist: daytona==0.103.0; extra == 'daytona'
Provides-Extra: dev
Requires-Dist: black>=23.0.0; extra == 'dev'
Requires-Dist: mypy>=1.5.0; extra == 'dev'
Requires-Dist: pre-commit>=3.0.0; extra == 'dev'
Requires-Dist: pytest-asyncio>=0.21.0; extra == 'dev'
Requires-Dist: pytest-cov>=4.1.0; extra == 'dev'
Requires-Dist: pytest>=7.4.0; extra == 'dev'
Requires-Dist: ruff>=0.1.0; extra == 'dev'
Provides-Extra: docs
Requires-Dist: mkdocs-material>=9.0.0; extra == 'docs'
Requires-Dist: mkdocs>=1.5.0; extra == 'docs'
Requires-Dist: mkdocstrings[python]>=0.20.0; extra == 'docs'
Provides-Extra: e2b
Requires-Dist: e2b>=2.0.0; extra == 'e2b'
Provides-Extra: hopx
Requires-Dist: hopx-ai>=0.3.0; extra == 'hopx'
Provides-Extra: modal
Requires-Dist: modal==1.1.4; extra == 'modal'
